dqn_ale_spaceinvaders/__init__.py
dqn_ale_spaceinvaders/agent.py
dqn_ale_spaceinvaders/buffer.py
dqn_ale_spaceinvaders/config.yaml
dqn_ale_spaceinvaders/enjoy.py
dqn_ale_spaceinvaders/environment.py
dqn_ale_spaceinvaders/export.py
dqn_ale_spaceinvaders/model.py
dqn_ale_spaceinvaders/train.py
dqn_ale_spaceinvaders/utils.py
dqn_ale_spaceinvaders-0.1.0.dist-info/LICENSE
dqn_ale_spaceinvaders-0.1.0.dist-info/METADATA
dqn_ale_spaceinvaders-0.1.0.dist-info/WHEEL
dqn_ale_spaceinvaders-0.1.0.dist-info/RECORD
