Metadata-Version: 2.1
Name: dqn-ale-spaceinvaders
Version: 0.1.0
Summary: A Deep Q-Network (DQN) implementation for Atari Space Invaders using Gymnasium and PyTorch.
Home-page: https://github.com/giansimone/dqn-ale-spaceinvaders
License: MIT
Keywords: reinforcement-learning,deep-reinforcement-learning,deep-q-learning-network,dqn,atari,gymnasium,space-invaders,arcade-learning-environment,ale,pytorch
Author: Giansimone Perrino
Author-email: hello@giansimone.dev
Requires-Python: >=3.13,<3.14
Classifier: Intended Audience :: Developers
Classifier: Intended Audience :: Science/Research
Classifier: License :: OSI Approved :: MIT License
Classifier: Operating System :: OS Independent
Classifier: Programming Language :: Python :: 3
Classifier: Programming Language :: Python :: 3.13
Classifier: Topic :: Scientific/Engineering :: Artificial Intelligence
Requires-Dist: gymnasium[accept-rom-license,atari] (>=1.2.1,<2.0.0)
Requires-Dist: huggingface-hub (>=0.35.3,<0.36.0)
Requires-Dist: imageio[ffmpeg] (>=2.37.0,<3.0.0)
Requires-Dist: opencv-python (>=4.12.0.88,<5.0.0.0)
Requires-Dist: tensorboard (>=2.20.0,<3.0.0)
Requires-Dist: torch (>=2.8.0,<3.0.0)
Requires-Dist: tqdm (>=4.67.1,<5.0.0)
Project-URL: Repository, https://github.com/giansimone/dqn-ale-spaceinvaders
